dbgear/__init__.py
dbgear/dbio/__init__.py
dbgear/dbio/database.py
dbgear/dbio/engine.py
dbgear/dbio/procedure.py
dbgear/dbio/table.py
dbgear/dbio/templates/__init__.py
dbgear/dbio/templates/engine.py
dbgear/dbio/templates/mysql/__init__.py
dbgear/dbio/trigger.py
dbgear/dbio/view.py
dbgear/importer.py
dbgear/main.py
dbgear/misc/__init__.py
dbgear/misc/a5sql_mk2.py
dbgear/misc/dependencies.py
dbgear/models/__init__.py
dbgear/models/base.py
dbgear/models/column.py
dbgear/models/column_type.py
dbgear/models/datamodel.py
dbgear/models/datasources/__init__.py
dbgear/models/datasources/base.py
dbgear/models/datasources/factory.py
dbgear/models/datasources/xlsxsource.py
dbgear/models/datasources/yamlsource.py
dbgear/models/environ.py
dbgear/models/exceptions.py
dbgear/models/index.py
dbgear/models/mapping.py
dbgear/models/notes.py
dbgear/models/option.py
dbgear/models/procedure.py
dbgear/models/project.py
dbgear/models/relation.py
dbgear/models/schema.py
dbgear/models/table.py
dbgear/models/tenant.py
dbgear/models/trigger.py
dbgear/models/view.py
dbgear/operations.py
dbgear/patch.py
dbgear/utils/__init__.py
dbgear/utils/const.py
dbgear/utils/dependency.py
dbgear/utils/dict_utils.py
dbgear/utils/fileio.py
dbgear/utils/populate.py
dbgear-0.41.0.dist-info/METADATA
dbgear-0.41.0.dist-info/WHEEL
dbgear-0.41.0.dist-info/entry_points.txt
dbgear-0.41.0.dist-info/licenses/LICENSE
dbgear-0.41.0.dist-info/RECORD
