Metadata-Version: 2.4
Name: dbgear
Version: 0.41.0
Summary: Database management tools for initial data management
License: MIT
License-File: LICENSE
Author: tamuto
Author-email: tamuto@infodb.jp
Requires-Python: >=3.12,<4.0
Classifier: License :: OSI Approved :: MIT License
Classifier: Programming Language :: Python :: 3
Classifier: Programming Language :: Python :: 3.12
Classifier: Programming Language :: Python :: 3.13
Classifier: Programming Language :: Python :: 3.14
Provides-Extra: xlsx
Requires-Dist: cryptography (>=42.0.7,<43.0.0)
Requires-Dist: jinja2 (>=3.1.6,<4.0.0)
Requires-Dist: openpyxl (>=3.1.5,<4.0.0) ; extra == "xlsx"
Requires-Dist: pydantic (>=2.0.0,<3.0.0)
Requires-Dist: pymysql (>=1.1.1,<2.0.0)
Requires-Dist: python-ulid (>=2.5.0,<3.0.0)
Requires-Dist: pyyaml (>=6.0,<7.0)
Requires-Dist: sqlalchemy (>=2.0.38,<3.0.0)
Project-URL: Homepage, https://github.com/tamuto/dbgear
Project-URL: Repository, https://github.com/tamuto/dbgear
